<annotation>
  <folder>VOC2007</folder>
  <filename>00000989</filename>
  <size>
    <width>1440</width>
    <height>2560</height>
    <depth>3</depth>
  </size>
  <object>
    <name>Text</name>
    <pose>Unspecified</pose>
    <truncated>0</truncated>
    <difficult>0</difficult>
    <bndbox>
      <xmin>28</xmin>
      <ymin> 703</ymin>
      <xmax> 1342</xmax>
      <ymax> 913</ymax>
    </bndbox>
  </object>
  <object>
    <name>Header</name>
    <pose>Unspecified</pose>
    <truncated>0</truncated>
    <difficult>0</difficult>
    <bndbox>
      <xmin>0</xmin>
      <ymin> 84</ymin>
      <xmax> 1440</xmax>
      <ymax> 277</ymax>
    </bndbox>
  </object>
  <object>
    <name>Button</name>
    <pose>Unspecified</pose>
    <truncated>0</truncated>
    <difficult>0</difficult>
    <bndbox>
      <xmin>18</xmin>
      <ymin> 119</ymin>
      <xmax> 277</xmax>
      <ymax> 242</ymax>
    </bndbox>
  </object>
  <object>
    <name>Text</name>
    <pose>Unspecified</pose>
    <truncated>0</truncated>
    <difficult>0</difficult>
    <bndbox>
      <xmin>558</xmin>
      <ymin> 138</ymin>
      <xmax> 881</xmax>
      <ymax> 223</ymax>
    </bndbox>
  </object>
  <object>
    <name>Button</name>
    <pose>Unspecified</pose>
    <truncated>0</truncated>
    <difficult>0</difficult>
    <bndbox>
      <xmin>1307</xmin>
      <ymin> 128</ymin>
      <xmax> 1412</xmax>
      <ymax> 233</ymax>
    </bndbox>
  </object>
  <object>
    <name>Text</name>
    <pose>Unspecified</pose>
    <truncated>0</truncated>
    <difficult>0</difficult>
    <bndbox>
      <xmin>70</xmin>
      <ymin> 452</ymin>
      <xmax> 1370</xmax>
      <ymax> 528</ymax>
    </bndbox>
  </object>
  <object>
    <name>Button</name>
    <pose>Unspecified</pose>
    <truncated>0</truncated>
    <difficult>0</difficult>
    <bndbox>
      <xmin>0</xmin>
      <ymin> 2199</ymin>
      <xmax> 1440</xmax>
      <ymax> 2392</ymax>
    </bndbox>
  </object>
  <object>
    <name>Image</name>
    <pose>Unspecified</pose>
    <truncated>0</truncated>
    <difficult>0</difficult>
    <bndbox>
      <xmin>1370</xmin>
      <ymin> 774</ymin>
      <xmax> 1412</xmax>
      <ymax> 841</ymax>
    </bndbox>
  </object>
  <object>
    <name>Text</name>
    <pose>Unspecified</pose>
    <truncated>0</truncated>
    <difficult>0</difficult>
    <bndbox>
      <xmin>28</xmin>
      <ymin> 913</ymin>
      <xmax> 1179</xmax>
      <ymax> 1123</ymax>
    </bndbox>
  </object>
  <object>
    <name>Text</name>
    <pose>Unspecified</pose>
    <truncated>0</truncated>
    <difficult>0</difficult>
    <bndbox>
      <xmin>1225</xmin>
      <ymin> 913</ymin>
      <xmax> 1356</xmax>
      <ymax> 1123</ymax>
    </bndbox>
  </object>
  <object>
    <name>Image</name>
    <pose>Unspecified</pose>
    <truncated>0</truncated>
    <difficult>0</difficult>
    <bndbox>
      <xmin>1384</xmin>
      <ymin> 996</ymin>
      <xmax> 1412</xmax>
      <ymax> 1040</ymax>
    </bndbox>
  </object>
</annotation>
