<annotation>
  <folder>VOC2007</folder>
  <filename>00000993</filename>
  <size>
    <width>1440</width>
    <height>2560</height>
    <depth>3</depth>
  </size>
  <object>
    <name>Text</name>
    <pose>Unspecified</pose>
    <truncated>0</truncated>
    <difficult>0</difficult>
    <bndbox>
      <xmin>238</xmin>
      <ymin> 252</ymin>
      <xmax> 1405</xmax>
      <ymax> 371</ymax>
    </bndbox>
  </object>
  <object>
    <name>Bar</name>
    <pose>Unspecified</pose>
    <truncated>0</truncated>
    <difficult>0</difficult>
    <bndbox>
      <xmin>0</xmin>
      <ymin> 84</ymin>
      <xmax> 1440</xmax>
      <ymax> 679</ymax>
    </bndbox>
  </object>
  <object>
    <name>Image</name>
    <pose>Unspecified</pose>
    <truncated>0</truncated>
    <difficult>0</difficult>
    <bndbox>
      <xmin>0</xmin>
      <ymin> 84</ymin>
      <xmax> 1440</xmax>
      <ymax> 511</ymax>
    </bndbox>
  </object>
  <object>
    <name>Header</name>
    <pose>Unspecified</pose>
    <truncated>0</truncated>
    <difficult>0</difficult>
    <bndbox>
      <xmin>35</xmin>
      <ymin> 252</ymin>
      <xmax> 1405</xmax>
      <ymax> 483</ymax>
    </bndbox>
  </object>
  <object>
    <name>Image</name>
    <pose>Unspecified</pose>
    <truncated>0</truncated>
    <difficult>0</difficult>
    <bndbox>
      <xmin>35</xmin>
      <ymin> 252</ymin>
      <xmax> 210</xmax>
      <ymax> 483</ymax>
    </bndbox>
  </object>
  <object>
    <name>Text</name>
    <pose>Unspecified</pose>
    <truncated>0</truncated>
    <difficult>0</difficult>
    <bndbox>
      <xmin>238</xmin>
      <ymin> 380</ymin>
      <xmax> 1405</xmax>
      <ymax> 483</ymax>
    </bndbox>
  </object>
  <object>
    <name>Image</name>
    <pose>Unspecified</pose>
    <truncated>0</truncated>
    <difficult>0</difficult>
    <bndbox>
      <xmin>18</xmin>
      <ymin> 688</ymin>
      <xmax> 1422</xmax>
      <ymax> 1477</ymax>
    </bndbox>
  </object>
  <object>
    <name>Bar</name>
    <pose>Unspecified</pose>
    <truncated>0</truncated>
    <difficult>0</difficult>
    <bndbox>
      <xmin>632</xmin>
      <ymin> 995</ymin>
      <xmax> 807</xmax>
      <ymax> 1170</ymax>
    </bndbox>
  </object>
  <object>
    <name>Button</name>
    <pose>Unspecified</pose>
    <truncated>0</truncated>
    <difficult>0</difficult>
    <bndbox>
      <xmin>0</xmin>
      <ymin> 2224</ymin>
      <xmax> 1440</xmax>
      <ymax> 2392</ymax>
    </bndbox>
  </object>
  <object>
    <name>Button</name>
    <pose>Unspecified</pose>
    <truncated>0</truncated>
    <difficult>0</difficult>
    <bndbox>
      <xmin>458</xmin>
      <ymin> 2226</ymin>
      <xmax> 981</xmax>
      <ymax> 2389</ymax>
    </bndbox>
  </object>
  <object>
    <name>Bar</name>
    <pose>Unspecified</pose>
    <truncated>0</truncated>
    <difficult>0</difficult>
    <bndbox>
      <xmin>0</xmin>
      <ymin> 84</ymin>
      <xmax> 1440</xmax>
      <ymax> 280</ymax>
    </bndbox>
  </object>
  <object>
    <name>Image</name>
    <pose>Unspecified</pose>
    <truncated>0</truncated>
    <difficult>0</difficult>
    <bndbox>
      <xmin>1286</xmin>
      <ymin> 126</ymin>
      <xmax> 1398</xmax>
      <ymax> 238</ymax>
    </bndbox>
  </object>
  <object>
    <name>Text</name>
    <pose>Unspecified</pose>
    <truncated>0</truncated>
    <difficult>0</difficult>
    <bndbox>
      <xmin>1349</xmin>
      <ymin> 119</ymin>
      <xmax> 1405</xmax>
      <ymax> 175</ymax>
    </bndbox>
  </object>
  <object>
    <name>NavigationBar</name>
    <pose>Unspecified</pose>
    <truncated>0</truncated>
    <difficult>0</difficult>
    <bndbox>
      <xmin>0</xmin>
      <ymin> 2392</ymin>
      <xmax> 1440</xmax>
      <ymax> 2560</ymax>
    </bndbox>
  </object>
  <object>
    <name>StatusBar</name>
    <pose>Unspecified</pose>
    <truncated>0</truncated>
    <difficult>0</difficult>
    <bndbox>
      <xmin>0</xmin>
      <ymin> 0</ymin>
      <xmax> 1440</xmax>
      <ymax> 84</ymax>
    </bndbox>
  </object>
</annotation>
