<annotation>
  <folder>VOC2007</folder>
  <filename>00000142</filename>
  <size>
    <width>1440</width>
    <height>2560</height>
    <depth>3</depth>
  </size>
  <object>
    <name>Image</name>
    <pose>Unspecified</pose>
    <truncated>0</truncated>
    <difficult>0</difficult>
    <bndbox>
      <xmin>35</xmin>
      <ymin> 461</ymin>
      <xmax> 1403</xmax>
      <ymax> 922</ymax>
    </bndbox>
  </object>
  <object>
    <name>Text</name>
    <pose>Unspecified</pose>
    <truncated>0</truncated>
    <difficult>0</difficult>
    <bndbox>
      <xmin>35</xmin>
      <ymin> 902</ymin>
      <xmax> 1403</xmax>
      <ymax> 1070</ymax>
    </bndbox>
  </object>
  <object>
    <name>Image</name>
    <pose>Unspecified</pose>
    <truncated>0</truncated>
    <difficult>0</difficult>
    <bndbox>
      <xmin>35</xmin>
      <ymin> 1110</ymin>
      <xmax> 1403</xmax>
      <ymax> 1571</ymax>
    </bndbox>
  </object>
  <object>
    <name>Text</name>
    <pose>Unspecified</pose>
    <truncated>0</truncated>
    <difficult>0</difficult>
    <bndbox>
      <xmin>35</xmin>
      <ymin> 1551</ymin>
      <xmax> 1403</xmax>
      <ymax> 1719</ymax>
    </bndbox>
  </object>
  <object>
    <name>Image</name>
    <pose>Unspecified</pose>
    <truncated>0</truncated>
    <difficult>0</difficult>
    <bndbox>
      <xmin>35</xmin>
      <ymin> 1759</ymin>
      <xmax> 1403</xmax>
      <ymax> 2196</ymax>
    </bndbox>
  </object>
  <object>
    <name>Text</name>
    <pose>Unspecified</pose>
    <truncated>0</truncated>
    <difficult>0</difficult>
    <bndbox>
      <xmin>0</xmin>
      <ymin> 1888</ymin>
      <xmax> 1440</xmax>
      <ymax> 2224</ymax>
    </bndbox>
  </object>
  <object>
    <name>Text</name>
    <pose>Unspecified</pose>
    <truncated>0</truncated>
    <difficult>0</difficult>
    <bndbox>
      <xmin>210</xmin>
      <ymin> 983</ymin>
      <xmax> 1230</xmax>
      <ymax> 1242</ymax>
    </bndbox>
  </object>
  <object>
    <name>Bar</name>
    <pose>Unspecified</pose>
    <truncated>0</truncated>
    <difficult>0</difficult>
    <bndbox>
      <xmin>0</xmin>
      <ymin> 84</ymin>
      <xmax> 1440</xmax>
      <ymax> 280</ymax>
    </bndbox>
  </object>
  <object>
    <name>Text</name>
    <pose>Unspecified</pose>
    <truncated>0</truncated>
    <difficult>0</difficult>
    <bndbox>
      <xmin>56</xmin>
      <ymin> 84</ymin>
      <xmax> 1272</xmax>
      <ymax> 280</ymax>
    </bndbox>
  </object>
  <object>
    <name>Button</name>
    <pose>Unspecified</pose>
    <truncated>0</truncated>
    <difficult>0</difficult>
    <bndbox>
      <xmin>1272</xmin>
      <ymin> 84</ymin>
      <xmax> 1440</xmax>
      <ymax> 280</ymax>
    </bndbox>
  </object>
  <object>
    <name>Bar</name>
    <pose>Unspecified</pose>
    <truncated>0</truncated>
    <difficult>0</difficult>
    <bndbox>
      <xmin>0</xmin>
      <ymin> 2196</ymin>
      <xmax> 1440</xmax>
      <ymax> 2392</ymax>
    </bndbox>
  </object>
  <object>
    <name>Text</name>
    <pose>Unspecified</pose>
    <truncated>0</truncated>
    <difficult>0</difficult>
    <bndbox>
      <xmin>151</xmin>
      <ymin> 2228</ymin>
      <xmax> 1440</xmax>
      <ymax> 2392</ymax>
    </bndbox>
  </object>
  <object>
    <name>Button</name>
    <pose>Unspecified</pose>
    <truncated>0</truncated>
    <difficult>0</difficult>
    <bndbox>
      <xmin>210</xmin>
      <ymin> 815</ymin>
      <xmax> 1230</xmax>
      <ymax> 1242</ymax>
    </bndbox>
  </object>
  <object>
    <name>Image</name>
    <pose>Unspecified</pose>
    <truncated>0</truncated>
    <difficult>0</difficult>
    <bndbox>
      <xmin>381</xmin>
      <ymin> 815</ymin>
      <xmax> 549</xmax>
      <ymax> 983</ymax>
    </bndbox>
  </object>
  <object>
    <name>Image</name>
    <pose>Unspecified</pose>
    <truncated>0</truncated>
    <difficult>0</difficult>
    <bndbox>
      <xmin>891</xmin>
      <ymin> 815</ymin>
      <xmax> 1059</xmax>
      <ymax> 983</ymax>
    </bndbox>
  </object>
  <object>
    <name>Text</name>
    <pose>Unspecified</pose>
    <truncated>0</truncated>
    <difficult>0</difficult>
    <bndbox>
      <xmin>210</xmin>
      <ymin> 1277</ymin>
      <xmax> 1230</xmax>
      <ymax> 1470</ymax>
    </bndbox>
  </object>
  <object>
    <name>NavigationBar</name>
    <pose>Unspecified</pose>
    <truncated>0</truncated>
    <difficult>0</difficult>
    <bndbox>
      <xmin>0</xmin>
      <ymin> 2392</ymin>
      <xmax> 1440</xmax>
      <ymax> 2560</ymax>
    </bndbox>
  </object>
  <object>
    <name>StatusBar</name>
    <pose>Unspecified</pose>
    <truncated>0</truncated>
    <difficult>0</difficult>
    <bndbox>
      <xmin>0</xmin>
      <ymin> 0</ymin>
      <xmax> 1440</xmax>
      <ymax> 84</ymax>
    </bndbox>
  </object>
</annotation>
