<annotation>
  <folder>VOC2007</folder>
  <filename>00000502</filename>
  <size>
    <width>1440</width>
    <height>2560</height>
    <depth>3</depth>
  </size>
  <object>
    <name>Image</name>
    <pose>Unspecified</pose>
    <truncated>0</truncated>
    <difficult>0</difficult>
    <bndbox>
      <xmin>141</xmin>
      <ymin> 358</ymin>
      <xmax> 1299</xmax>
      <ymax> 1793</ymax>
    </bndbox>
  </object>
  <object>
    <name>Image</name>
    <pose>Unspecified</pose>
    <truncated>0</truncated>
    <difficult>0</difficult>
    <bndbox>
      <xmin>636</xmin>
      <ymin> 1888</ymin>
      <xmax> 803</xmax>
      <ymax> 2055</ymax>
    </bndbox>
  </object>
</annotation>
