<annotation>
  <folder>VOC2007</folder>
  <filename>00000003</filename>
  <size>
    <width>1440</width>
    <height>2560</height>
    <depth>3</depth>
  </size>
  <object>
    <name>Text</name>
    <pose>Unspecified</pose>
    <truncated>0</truncated>
    <difficult>0</difficult>
    <bndbox>
      <xmin>0</xmin>
      <ymin> 1593</ymin>
      <xmax> 1440</xmax>
      <ymax> 1659</ymax>
    </bndbox>
  </object>
  <object>
    <name>Text</name>
    <pose>Unspecified</pose>
    <truncated>0</truncated>
    <difficult>0</difficult>
    <bndbox>
      <xmin>35</xmin>
      <ymin> 2129</ymin>
      <xmax> 814</xmax>
      <ymax> 2298</ymax>
    </bndbox>
  </object>
  <object>
    <name>Text</name>
    <pose>Unspecified</pose>
    <truncated>0</truncated>
    <difficult>0</difficult>
    <bndbox>
      <xmin>35</xmin>
      <ymin> 2333</ymin>
      <xmax> 688</xmax>
      <ymax> 2392</ymax>
    </bndbox>
  </object>
  <object>
    <name>Bar</name>
    <pose>Unspecified</pose>
    <truncated>0</truncated>
    <difficult>0</difficult>
    <bndbox>
      <xmin>0</xmin>
      <ymin> 84</ymin>
      <xmax> 1440</xmax>
      <ymax> 889</ymax>
    </bndbox>
  </object>
  <object>
    <name>Bar</name>
    <pose>Unspecified</pose>
    <truncated>0</truncated>
    <difficult>0</difficult>
    <bndbox>
      <xmin>0</xmin>
      <ymin> 84</ymin>
      <xmax> 1440</xmax>
      <ymax> 280</ymax>
    </bndbox>
  </object>
  <object>
    <name>Text</name>
    <pose>Unspecified</pose>
    <truncated>0</truncated>
    <difficult>0</difficult>
    <bndbox>
      <xmin>450</xmin>
      <ymin> 903</ymin>
      <xmax> 1440</xmax>
      <ymax> 969</ymax>
    </bndbox>
  </object>
  <object>
    <name>Text</name>
    <pose>Unspecified</pose>
    <truncated>0</truncated>
    <difficult>0</difficult>
    <bndbox>
      <xmin>28</xmin>
      <ymin> 969</ymin>
      <xmax> 1440</xmax>
      <ymax> 1109</ymax>
    </bndbox>
  </object>
  <object>
    <name>Text</name>
    <pose>Unspecified</pose>
    <truncated>0</truncated>
    <difficult>0</difficult>
    <bndbox>
      <xmin>28</xmin>
      <ymin> 1109</ymin>
      <xmax> 457</xmax>
      <ymax> 1175</ymax>
    </bndbox>
  </object>
  <object>
    <name>Text</name>
    <pose>Unspecified</pose>
    <truncated>0</truncated>
    <difficult>0</difficult>
    <bndbox>
      <xmin>28</xmin>
      <ymin> 1189</ymin>
      <xmax> 1440</xmax>
      <ymax> 1278</ymax>
    </bndbox>
  </object>
  <object>
    <name>Text</name>
    <pose>Unspecified</pose>
    <truncated>0</truncated>
    <difficult>0</difficult>
    <bndbox>
      <xmin>0</xmin>
      <ymin> 1782</ymin>
      <xmax> 1440</xmax>
      <ymax> 1876</ymax>
    </bndbox>
  </object>
  <object>
    <name>Bar</name>
    <pose>Unspecified</pose>
    <truncated>0</truncated>
    <difficult>0</difficult>
    <bndbox>
      <xmin>0</xmin>
      <ymin> 1250</ymin>
      <xmax> 1440</xmax>
      <ymax> 1418</ymax>
    </bndbox>
  </object>
  <object>
    <name>Button</name>
    <pose>Unspecified</pose>
    <truncated>0</truncated>
    <difficult>0</difficult>
    <bndbox>
      <xmin>1209</xmin>
      <ymin> 2161</ymin>
      <xmax> 1405</xmax>
      <ymax> 2357</ymax>
    </bndbox>
  </object>
  <object>
    <name>Text</name>
    <pose>Unspecified</pose>
    <truncated>0</truncated>
    <difficult>0</difficult>
    <bndbox>
      <xmin>626</xmin>
      <ymin> 2267</ymin>
      <xmax> 904</xmax>
      <ymax> 2342</ymax>
    </bndbox>
  </object>
  <object>
    <name>NavigationBar</name>
    <pose>Unspecified</pose>
    <truncated>0</truncated>
    <difficult>0</difficult>
    <bndbox>
      <xmin>0</xmin>
      <ymin> 2392</ymin>
      <xmax> 1440</xmax>
      <ymax> 2560</ymax>
    </bndbox>
  </object>
  <object>
    <name>StatusBar</name>
    <pose>Unspecified</pose>
    <truncated>0</truncated>
    <difficult>0</difficult>
    <bndbox>
      <xmin>0</xmin>
      <ymin> 0</ymin>
      <xmax> 1440</xmax>
      <ymax> 84</ymax>
    </bndbox>
  </object>
</annotation>
