<annotation>
  <folder>VOC2007</folder>
  <filename>00000092</filename>
  <size>
    <width>1440</width>
    <height>2560</height>
    <depth>3</depth>
  </size>
  <object>
    <name>Video</name>
    <pose>Unspecified</pose>
    <truncated>0</truncated>
    <difficult>0</difficult>
    <bndbox>
      <xmin>650</xmin>
      <ymin> 585</ymin>
      <xmax> 790</xmax>
      <ymax> 802</ymax>
    </bndbox>
  </object>
  <object>
    <name>Video</name>
    <pose>Unspecified</pose>
    <truncated>0</truncated>
    <difficult>0</difficult>
    <bndbox>
      <xmin>88</xmin>
      <ymin> 339</ymin>
      <xmax> 1352</xmax>
      <ymax> 1050</ymax>
    </bndbox>
  </object>
  <object>
    <name>Video</name>
    <pose>Unspecified</pose>
    <truncated>0</truncated>
    <difficult>0</difficult>
    <bndbox>
      <xmin>176</xmin>
      <ymin> 1106</ymin>
      <xmax> 1264</xmax>
      <ymax> 1240</ymax>
    </bndbox>
  </object>
  <object>
    <name>Image</name>
    <pose>Unspecified</pose>
    <truncated>0</truncated>
    <difficult>0</difficult>
    <bndbox>
      <xmin>88</xmin>
      <ymin> 2207</ymin>
      <xmax> 1352</xmax>
      <ymax> 2392</ymax>
    </bndbox>
  </object>
  <object>
    <name>Text</name>
    <pose>Unspecified</pose>
    <truncated>0</truncated>
    <difficult>0</difficult>
    <bndbox>
      <xmin>474</xmin>
      <ymin> 2271</ymin>
      <xmax> 966</xmax>
      <ymax> 2337</ymax>
    </bndbox>
  </object>
  <object>
    <name>Image</name>
    <pose>Unspecified</pose>
    <truncated>0</truncated>
    <difficult>0</difficult>
    <bndbox>
      <xmin>1019</xmin>
      <ymin> 2288</ymin>
      <xmax> 1058</xmax>
      <ymax> 2320</ymax>
    </bndbox>
  </object>
  <object>
    <name>NavigationBar</name>
    <pose>Unspecified</pose>
    <truncated>0</truncated>
    <difficult>0</difficult>
    <bndbox>
      <xmin>0</xmin>
      <ymin> 84</ymin>
      <xmax> 1440</xmax>
      <ymax> 280</ymax>
    </bndbox>
  </object>
  <object>
    <name>Button</name>
    <pose>Unspecified</pose>
    <truncated>0</truncated>
    <difficult>0</difficult>
    <bndbox>
      <xmin>964</xmin>
      <ymin> 98</ymin>
      <xmax> 1132</xmax>
      <ymax> 266</ymax>
    </bndbox>
  </object>
  <object>
    <name>NavigationBar</name>
    <pose>Unspecified</pose>
    <truncated>0</truncated>
    <difficult>0</difficult>
    <bndbox>
      <xmin>0</xmin>
      <ymin> 2392</ymin>
      <xmax> 1440</xmax>
      <ymax> 2560</ymax>
    </bndbox>
  </object>
  <object>
    <name>StatusBar</name>
    <pose>Unspecified</pose>
    <truncated>0</truncated>
    <difficult>0</difficult>
    <bndbox>
      <xmin>0</xmin>
      <ymin> 0</ymin>
      <xmax> 1440</xmax>
      <ymax> 84</ymax>
    </bndbox>
  </object>
</annotation>
