<annotation>
  <folder>VOC2007</folder>
  <filename>00000309</filename>
  <size>
    <width>1440</width>
    <height>2560</height>
    <depth>3</depth>
  </size>
  <object>
    <name>Image</name>
    <pose>Unspecified</pose>
    <truncated>0</truncated>
    <difficult>0</difficult>
    <bndbox>
      <xmin>685</xmin>
      <ymin> 1591</ymin>
      <xmax> 755</xmax>
      <ymax> 1626</ymax>
    </bndbox>
  </object>
  <object>
    <name>Image</name>
    <pose>Unspecified</pose>
    <truncated>0</truncated>
    <difficult>0</difficult>
    <bndbox>
      <xmin>35</xmin>
      <ymin> 1676</ymin>
      <xmax> 98</xmax>
      <ymax> 1739</ymax>
    </bndbox>
  </object>
  <object>
    <name>Text</name>
    <pose>Unspecified</pose>
    <truncated>0</truncated>
    <difficult>0</difficult>
    <bndbox>
      <xmin>116</xmin>
      <ymin> 1661</ymin>
      <xmax> 1405</xmax>
      <ymax> 1754</ymax>
    </bndbox>
  </object>
  <object>
    <name>Text</name>
    <pose>Unspecified</pose>
    <truncated>0</truncated>
    <difficult>0</difficult>
    <bndbox>
      <xmin>178</xmin>
      <ymin> 1789</ymin>
      <xmax> 1262</xmax>
      <ymax> 2155</ymax>
    </bndbox>
  </object>
  <object>
    <name>Button</name>
    <pose>Unspecified</pose>
    <truncated>0</truncated>
    <difficult>0</difficult>
    <bndbox>
      <xmin>510</xmin>
      <ymin> 2225</ymin>
      <xmax> 930</xmax>
      <ymax> 2357</ymax>
    </bndbox>
  </object>
</annotation>
